ehw/__init__.py
ehw/__main__.py
ehw/ehw.py
ehw-1.0.0.dist-info/METADATA
ehw-1.0.0.dist-info/WHEEL
ehw-1.0.0.dist-info/entry_points.txt
ehw-1.0.0.dist-info/top_level.txt
ehw-1.0.0.dist-info/RECORD
